qcausality/README.md
qcausality/__init__.py
qcausality-0.0.2.dist-info/WHEEL
qcausality-0.0.2.dist-info/METADATA
qcausality-0.0.2.dist-info/RECORD
